{
	"backtrace" : 0,
	"backtraceGraph" : 
	{
		"commands" : [],
		"files" : 
		[
			"src/opengl_painter/CMakeLists.txt"
		],
		"nodes" : 
		[
			{
				"file" : 0
			}
		]
	},
	"dependencies" : 
	[
		{
			"id" : "opengl_painter_autogen_timestamp_deps::@0cde7792ddf8ceed9157"
		}
	],
	"id" : "opengl_painter_autogen::@0cde7792ddf8ceed9157",
	"isGeneratorProvided" : true,
	"name" : "opengl_painter_autogen",
	"paths" : 
	{
		"build" : "src/opengl_painter",
		"source" : "src/opengl_painter"
	},
	"sourceGroups" : 
	[
		{
			"name" : "",
			"sourceIndexes" : 
			[
				0
			]
		},
		{
			"name" : "CMake Rules",
			"sourceIndexes" : 
			[
				1,
				2
			]
		}
	],
	"sources" : 
	[
		{
			"backtrace" : 0,
			"isGenerated" : true,
			"path" : "out/build/x64-Debug/src/opengl_painter/CMakeFiles/opengl_painter_autogen",
			"sourceGroupIndex" : 0
		},
		{
			"backtrace" : 0,
			"isGenerated" : true,
			"path" : "out/build/x64-Debug/src/opengl_painter/CMakeFiles/opengl_painter_autogen.rule",
			"sourceGroupIndex" : 1
		},
		{
			"backtrace" : 0,
			"isGenerated" : true,
			"path" : "out/build/x64-Debug/src/opengl_painter/opengl_painter_autogen/timestamp.rule",
			"sourceGroupIndex" : 1
		}
	],
	"type" : "UTILITY"
}
